riboclette/__init__.py
riboclette/main.py
riboclette/checkpoints/XLNet-PLabelDH_S2/best_model/config.json
riboclette/checkpoints/XLNet-PLabelDH_S2/best_model/model.safetensors
riboclette/checkpoints/XLNet-PLabelDH_S2/best_model/training_args.bin
riboclette/models/__init__.py
riboclette/preprocessing/__init__.py
riboclette/utils/__init__.py
riboclette/utils/loss.py
riboclette/utils/metrics.py
riboclette-0.1.1.dist-info/METADATA
riboclette-0.1.1.dist-info/WHEEL
riboclette-0.1.1.dist-info/top_level.txt
riboclette-0.1.1.dist-info/RECORD
