Metadata-Version: 2.2
Name: riboclette
Version: 0.1.1
Author: Vamsi Nallapareddy and Francesco Craighero
Requires-Dist: numpy>=1.26.4
Requires-Dist: transformers>=4.38.0
Requires-Dist: captum>=0.8.0
Provides-Extra: cuda
Requires-Dist: torch==2.6.0+cu118; extra == "cuda"
Provides-Extra: cpu
Requires-Dist: torch==2.6.0; extra == "cpu"
Dynamic: author
Dynamic: description
Dynamic: description-content-type
Dynamic: provides-extra
Dynamic: requires-dist
